brew_search-0.1.0.dist-info/METADATA
brew_search-0.1.0.dist-info/WHEEL
brew_search-0.1.0.dist-info/entry_points.txt
brew_search/__init__.py
brew_search/__main__.py
brew_search-0.1.0.dist-info/RECORD
