Metadata-Version: 2.1
Name: brew-search
Version: 0.1.0
Summary: Search CLI tool for Homebrew (support sorting by popularity)
Author-Email: strayge <strayge@gmail.com>
License: MIT
Classifier: Development Status :: 4 - Beta
Classifier: Intended Audience :: Developers
Classifier: Natural Language :: English
Classifier: Environment :: Console
Classifier: License :: OSI Approved :: MIT License
Classifier: Programming Language :: Python :: 3.10
Classifier: Programming Language :: Python :: 3.11
Classifier: Programming Language :: Python :: Implementation :: CPython
Classifier: Topic :: Utilities
Project-URL: Repository, https://github.com/strayge/pybrew
Requires-Python: >=3.10
Requires-Dist: httpx
Requires-Dist: colorama
Requires-Dist: flake8-pyproject; extra == "dev"
Requires-Dist: flake8-commas; extra == "dev"
Requires-Dist: flake8-isort; extra == "dev"
Requires-Dist: flake8-bugbear; extra == "dev"
Requires-Dist: flake8-simplify; extra == "dev"
Requires-Dist: flake8-print; extra == "dev"
Requires-Dist: flake8-debugger; extra == "dev"
Requires-Dist: flake8-fixme; extra == "dev"
Requires-Dist: flake8-leading-blank-lines; extra == "dev"
Requires-Dist: isort; extra == "dev"
Requires-Dist: mypy; extra == "dev"
Provides-Extra: dev
